safarnama/__init__.py
safarnama/config.py
safarnama/crawler.py
safarnama/db.py
safarnama/html_cleaner.py
safarnama/logger_setup.py
safarnama/main.py
safarnama/searcher.py
safarnama-0.2.2.dist-info/METADATA
safarnama-0.2.2.dist-info/WHEEL
safarnama-0.2.2.dist-info/entry_points.txt
safarnama-0.2.2.dist-info/licenses/LICENSE
safarnama-0.2.2.dist-info/RECORD
