Metadata-Version: 2.4
Name: Safarnama
Version: 0.2.2
Summary: Safarnama is a versatile web crawler that explores websites, cleans HTML, and uses a language model to generate summaries and tags—writing its own digital story. Use it via CLI or in Python projects.
Author-email: Ali Tavallaie <a.tavallaie@gmail.com>
License: MIT License
License-File: LICENSE
Requires-Python: >=3.10
Requires-Dist: bs4>=0.0.2
Requires-Dist: httpx>=0.28.1
Requires-Dist: loguru>=0.7.3
Requires-Dist: pyyaml>=6.0.2
Requires-Dist: sqlalchemy>=2.0.38
Requires-Dist: typer>=0.15.1
